{"cmdline":"mmul_tiled/mmul_TI=256_TK=512","arg_quiet":false,"arg_nruns":5,"arg_error":-0.1,"real_nruns":5,"real_error":.126095,"runs":[{"wall":24.30,"user":24.16,"system":0.01,"mem":99424},{"wall":24.81,"user":24.66,"system":0.02,"mem":99400},{"wall":24.13,"user":23.99,"system":0.02,"mem":99444},{"wall":24.69,"user":24.55,"system":0.01,"mem":99424},{"wall":24.37,"user":24.23,"system":0.01,"mem":99552}],"mean":{"wall":24.460,"user":24.318,"system":0.014,"mem":99448.800},"variance":{"wall":0.079,"user":0.078,"system":0.000,"mem":3571.200}}