{"cmdline":"mmul_tiled/mmul_TI=512_TK=128","arg_quiet":false,"arg_nruns":5,"arg_error":-0.1,"real_nruns":5,"real_error":.082133,"runs":[{"wall":24.51,"user":24.39,"system":0.02,"mem":99444},{"wall":24.62,"user":24.51,"system":0.02,"mem":99412},{"wall":24.20,"user":24.10,"system":0.01,"mem":99372},{"wall":24.64,"user":24.53,"system":0.02,"mem":99440},{"wall":24.61,"user":24.50,"system":0.02,"mem":99428}],"mean":{"wall":24.516,"user":24.406,"system":0.018,"mem":99419.200},"variance":{"wall":0.034,"user":0.032,"system":0.000,"mem":851.200}}