{"cmdline":"./mmul","arg_quiet":false,"arg_nruns":10,"arg_error":0.05,"real_nruns":8,"real_error":.047159,"runs":[{"wall":6.10,"user":6.07,"system":0.01,"mem":24584},{"wall":5.80,"user":5.78,"system":0.00,"mem":24588},{"wall":5.79,"user":5.76,"system":0.00,"mem":24656},{"wall":5.77,"user":5.74,"system":0.00,"mem":24536},{"wall":6.00,"user":5.97,"system":0.00,"mem":24544},{"wall":6.02,"user":5.99,"system":0.00,"mem":24548},{"wall":5.76,"user":5.74,"system":0.00,"mem":24568},{"wall":5.94,"user":5.92,"system":0.00,"mem":24584}],"mean":{"wall":5.897,"user":5.871,"system":0.001,"mem":24576.000},"variance":{"wall":0.018,"user":0.017,"system":0.000,"mem":1449.143}}